plover_oft_eva/__init__.py
plover_oft_eva/machine.py
plover_oft_eva/machine_option.py
plover_oft_eva/testing.py
plover_oft_eva-0.2.7.dist-info/METADATA
plover_oft_eva-0.2.7.dist-info/WHEEL
plover_oft_eva-0.2.7.dist-info/entry_points.txt
plover_oft_eva-0.2.7.dist-info/top_level.txt
plover_oft_eva-0.2.7.dist-info/zip-safe
plover_oft_eva-0.2.7.dist-info/RECORD
