Metadata-Version: 2.1
Name: plover-oft-eva
Version: 0.2.7
Summary: OFT EVA support for Plover
Home-page: https://github.com/benoit-pierre/plover_oft_eva
Author: Benoit Pierre
Author-email: benoit.pierre@gmail.com
License: GNU General Public License v2 or later (GPLv2+)
Project-URL: Source Code, https://github.com/benoit-pierre/plover_oft_eva
Project-URL: Issue Tracker, https://github.com/benoit-pierre/plover_oft_eva/issues
Keywords: plover plover_plugin
Platform: UNKNOWN
Classifier: Development Status :: 4 - Beta
Classifier: Environment :: Plugins
Classifier: Intended Audience :: End Users/Desktop
Classifier: License :: OSI Approved :: GNU General Public License v2 or later (GPLv2+)
Classifier: Operating System :: OS Independent
Classifier: Programming Language :: Python :: 3
Classifier: Programming Language :: Python :: 3.6
Classifier: Programming Language :: Python :: 3.7
Classifier: Programming Language :: Python :: 3.8
Classifier: Programming Language :: Python :: 3.9
Classifier: Programming Language :: Python :: 3.10
Requires-Dist: plover (>=4.0.0.dev6)
